README.rst
setup.py
lweb/__init__.py
lweb/core.py
lweb.egg-info/PKG-INFO
lweb.egg-info/SOURCES.txt
lweb.egg-info/dependency_links.txt
lweb.egg-info/top_level.txt