Metadata-Version: 1.1
Name: lweb
Version: 0.1.10
Summary: A light-weight python web framework, shameless copy from bottle.
Home-page: https://github.com/zii/lweb
Author: zii
Author-email: gamcat@gmail.com
License: MIT
Keywords: web framework
Platform: UNKNOWN
Classifier: Development Status :: 4 - Beta
Classifier: Intended Audience :: Developers
Classifier: Topic :: Software Development :: Build Tools
Classifier: License :: OSI Approved :: MIT License
Classifier: Programming Language :: Python :: 2.7
Classifier: Programming Language :: Python :: 3
